cfgeom/__init__.py
cfgeom/_version.py
cfgeom/container.py
cfgeom/geometry.py
cfgeom/part.py
cfgeom/util.py
cfgeom/convert/__init__.py
cfgeom/convert/json_io/__init__.py
cfgeom/convert/json_io/json_reader.py
cfgeom/convert/json_io/json_writer.py
cfgeom/convert/netcdf/__init__.py
cfgeom/convert/netcdf/nc_constants.py
cfgeom/convert/netcdf/nc_names.py
cfgeom/convert/netcdf/nc_reader.py
cfgeom/convert/netcdf/nc_writer.py
cfgeom/convert/shapely_io/__init__.py
cfgeom/convert/shapely_io/shapely_reader.py
cfgeom/convert/shapely_io/shapely_writer.py
cfgeom/test/__init__.py
cfgeom/test/base.py
cfgeom/test/test_base.py
cfgeom/test/test_ncgeom/__init__.py
cfgeom/test/test_ncgeom/test_container.py
cfgeom/test/test_ncgeom/test_geometry.py
cfgeom/test/test_ncgeom/test_part.py
cfgeom/test/test_ncgeom/test_convert/__init__.py
cfgeom/test/test_ncgeom/test_convert/test_json/__init__.py
cfgeom/test/test_ncgeom/test_convert/test_json/test_json.py
cfgeom/test/test_ncgeom/test_convert/test_netcdf/__init__.py
cfgeom/test/test_ncgeom/test_convert/test_netcdf/test_nc_reader.py
cfgeom/test/test_ncgeom/test_convert/test_netcdf/test_nc_writer.py
cfgeom/test/test_ncgeom/test_convert/test_shapely/__init__.py
cfgeom/test/test_ncgeom/test_convert/test_shapely/test_shapely_reader.py
cfgeom/test/test_ncgeom/test_convert/test_shapely/test_shapely_writer.py
cfgeom-0.2.0.dist-info/LICENSE
cfgeom-0.2.0.dist-info/METADATA
cfgeom-0.2.0.dist-info/WHEEL
cfgeom-0.2.0.dist-info/top_level.txt
cfgeom-0.2.0.dist-info/RECORD
