Metadata-Version: 2.1
Name: cfgeom
Version: 0.2.0
Summary: Reference implementation for representing geometries in NetCDF with the CF Conventions
Home-page: https://github.com/twhiteaker/CFGeom
Author: TIm Whiteaker
Author-email: whiteaker@utexas.edu
License: LICENSE
Platform: UNKNOWN
Classifier: Programming Language :: Python
Classifier: License :: OSI Approved :: MIT License
Classifier: Operating System :: OS Independent
Requires-Dist: shapely (>=1.6.4.post1)
Requires-Dist: numpy (>=1.9.3)
Requires-Dist: netcdf4 (>=1.0.8)
